<annotation>
	<folder>railway garbag</folder>
	<filename>25a66358-67a2-11e5-b0b2-40f2e96c8ad8.jpg</filename>
	<path>C:\garbage\spotgarbage-GINI\spotgarbage\garbage-queried-images\railway garbag\25a66358-67a2-11e5-b0b2-40f2e96c8ad8.jpg</path>
	<source>
		<database>Unknown</database>
	</source>
	<size>
		<width>630</width>
		<height>375</height>
		<depth>3</depth>
	</size>
	<segmented>0</segmented>
	<object>
		<name>garbage</name>
		<pose>Unspecified</pose>
		<truncated>0</truncated>
		<difficult>0</difficult>
		<bndbox>
			<xmin>273</xmin>
			<ymin>148</ymin>
			<xmax>621</xmax>
			<ymax>225</ymax>
		</bndbox>
	</object>
	<object>
		<name>garbage</name>
		<pose>Unspecified</pose>
		<truncated>0</truncated>
		<difficult>0</difficult>
		<bndbox>
			<xmin>27</xmin>
			<ymin>139</ymin>
			<xmax>77</xmax>
			<ymax>255</ymax>
		</bndbox>
	</object>
</annotation>
