<annotation>
	<folder>trash on roads</folder>
	<filename>9598b174-679e-11e5-b0d3-40f2e96c8ad8.jpg</filename>
	<path>C:\garbage\spotgarbage-GINI\spotgarbage\garbage-queried-images\trash on roads\9598b174-679e-11e5-b0d3-40f2e96c8ad8.jpg</path>
	<source>
		<database>Unknown</database>
	</source>
	<size>
		<width>500</width>
		<height>375</height>
		<depth>3</depth>
	</size>
	<segmented>0</segmented>
	<object>
		<name>garbage</name>
		<pose>Unspecified</pose>
		<truncated>0</truncated>
		<difficult>0</difficult>
		<bndbox>
			<xmin>231</xmin>
			<ymin>210</ymin>
			<xmax>402</xmax>
			<ymax>290</ymax>
		</bndbox>
	</object>
	<object>
		<name>garbage</name>
		<pose>Unspecified</pose>
		<truncated>0</truncated>
		<difficult>0</difficult>
		<bndbox>
			<xmin>308</xmin>
			<ymin>178</ymin>
			<xmax>477</xmax>
			<ymax>226</ymax>
		</bndbox>
	</object>
</annotation>
