<annotation>
	<folder>delhi garbage</folder>
	<filename>a92f6a34-6799-11e5-ba3c-40f2e96c8ad8.jpg</filename>
	<path>C:\garbage\spotgarbage-GINI\spotgarbage\garbage-queried-images\delhi garbage\a92f6a34-6799-11e5-ba3c-40f2e96c8ad8.jpg</path>
	<source>
		<database>Unknown</database>
	</source>
	<size>
		<width>759</width>
		<height>422</height>
		<depth>3</depth>
	</size>
	<segmented>0</segmented>
	<object>
		<name>garbage</name>
		<pose>Unspecified</pose>
		<truncated>0</truncated>
		<difficult>0</difficult>
		<bndbox>
			<xmin>61</xmin>
			<ymin>201</ymin>
			<xmax>733</xmax>
			<ymax>379</ymax>
		</bndbox>
	</object>
</annotation>
