<annotation>
	<folder>clothes</folder>
	<filename>45bd2fe8-9446-11e5-8185-40f2e96c8ad8.jpg</filename>
	<path>C:\garbage\spotgarbage-GINI\spotgarbage\non-garbage-queried-images\clothes\45bd2fe8-9446-11e5-8185-40f2e96c8ad8.jpg</path>
	<source>
		<database>Unknown</database>
	</source>
	<size>
		<width>600</width>
		<height>489</height>
		<depth>3</depth>
	</size>
	<segmented>0</segmented>
	<object>
		<name>clear</name>
		<pose>Unspecified</pose>
		<truncated>0</truncated>
		<difficult>0</difficult>
		<bndbox>
			<xmin>5</xmin>
			<ymin>14</ymin>
			<xmax>595</xmax>
			<ymax>472</ymax>
		</bndbox>
	</object>
</annotation>
