<annotation>
	<folder>clothes</folder>
	<filename>5dbaf15c-9446-11e5-8185-40f2e96c8ad8.jpg</filename>
	<path>C:\garbage\spotgarbage-GINI\spotgarbage\non-garbage-queried-images\clothes\5dbaf15c-9446-11e5-8185-40f2e96c8ad8.jpg</path>
	<source>
		<database>Unknown</database>
	</source>
	<size>
		<width>500</width>
		<height>500</height>
		<depth>3</depth>
	</size>
	<segmented>0</segmented>
	<object>
		<name>clear</name>
		<pose>Unspecified</pose>
		<truncated>1</truncated>
		<difficult>0</difficult>
		<bndbox>
			<xmin>2</xmin>
			<ymin>1</ymin>
			<xmax>498</xmax>
			<ymax>500</ymax>
		</bndbox>
	</object>
</annotation>
